nhtsa_vin_decoder-0.1.0.dist-info/licenses/LICENSE
python/__init__.py
python/nhtsa_vin_decoder.py
python/wmi_database.py
nhtsa_vin_decoder-0.1.0.dist-info/METADATA
nhtsa_vin_decoder-0.1.0.dist-info/WHEEL
nhtsa_vin_decoder-0.1.0.dist-info/top_level.txt
nhtsa_vin_decoder-0.1.0.dist-info/RECORD
