Metadata-Version: 2.4
Name: nhtsa-vin-decoder
Version: 0.1.0
Summary: World-class VIN decoder with comprehensive offline database (2,015+ WMI codes) and NHTSA vPIC API integration
Author-email: Wal33D <aquataze@yahoo.com>
License: MIT
Project-URL: Homepage, https://github.com/Wal33D/nhtsa-vin-decoder
Project-URL: Documentation, https://github.com/Wal33D/nhtsa-vin-decoder#readme
Project-URL: Repository, https://github.com/Wal33D/nhtsa-vin-decoder
Project-URL: Issues, https://github.com/Wal33D/nhtsa-vin-decoder/issues
Project-URL: Changelog, https://github.com/Wal33D/nhtsa-vin-decoder/blob/main/CHANGELOG.md
Keywords: vin,decoder,nhtsa,vehicle,automotive,obd2,vpic,wmi,vin-decoder,car,vehicle-identification,offline
Classifier: Development Status :: 4 - Beta
Classifier: Intended Audience :: Developers
Classifier: License :: OSI Approved :: MIT License
Classifier: Programming Language :: Python :: 3
Classifier: Programming Language :: Python :: 3.6
Classifier: Programming Language :: Python :: 3.7
Classifier: Programming Language :: Python :: 3.8
Classifier: Programming Language :: Python :: 3.9
Classifier: Programming Language :: Python :: 3.10
Classifier: Programming Language :: Python :: 3.11
Classifier: Programming Language :: Python :: 3.12
Classifier: Topic :: Software Development :: Libraries :: Python Modules
Classifier: Topic :: System :: Hardware :: Hardware Drivers
Classifier: Operating System :: OS Independent
Requires-Python: >=3.6
License-File: LICENSE
Provides-Extra: api
Requires-Dist: requests>=2.25.0; extra == "api"
Provides-Extra: dev
Requires-Dist: pytest>=6.0; extra == "dev"
Requires-Dist: pytest-cov>=2.10; extra == "dev"
Requires-Dist: black>=21.0; extra == "dev"
Requires-Dist: flake8>=3.9; extra == "dev"
Provides-Extra: web
Requires-Dist: flask>=2.0.0; extra == "web"
Requires-Dist: flask-cors>=3.0.10; extra == "web"
Dynamic: license-file
